fastapi_request_helper/__init__.py
fastapi_request_helper/constants/http_method.py
fastapi_request_helper/decorators/authentication.py
fastapi_request_helper/decorators/controller.py
fastapi_request_helper/decorators/http_method.py
fastapi_request_helper/dependencies/custom_query.py
fastapi_request_helper/dependencies/guard.py
fastapi_request_helper/dependencies/pagination.py
fastapi_request_helper/helpers/router_decorator.py
fastapi_request_helper-0.0.17.dist-info/METADATA
fastapi_request_helper-0.0.17.dist-info/WHEEL
fastapi_request_helper-0.0.17.dist-info/licenses/LICENSE
fastapi_request_helper-0.0.17.dist-info/RECORD
