Metadata-Version: 2.4
Name: fastapi_request_helper
Version: 0.0.17
Summary: FastAPI Request Helper
Project-URL: Homepage, https://github.com/megatron-global/fastapi-request-helper
Project-URL: Bug Tracker, https://github.com/megatron-global/fastapi-request-helper/issues
Author-email: Dzung Nguyen <dung@megatron-solutions.com>
License-File: LICENSE
Classifier: License :: OSI Approved :: MIT License
Classifier: Operating System :: OS Independent
Classifier: Programming Language :: Python :: 3
Requires-Python: >=3.10
Requires-Dist: fastapi-global-variable==0.0.4
Requires-Dist: fastapi-restful==0.5.0
Requires-Dist: fastapi>=0.103.1
